[
  {
    "rank": 1,
    "id": 18158896,
    "title": "InVision has no physical headquarters and all 700 employees work remotely",
    "url": "https://www.businessinsider.com/invision-startup-all-employees-work-remotely-2018-9",
    "score": 482,
    "by": "aviv",
    "descendants": 225,
    "time": 1538887772
  },
  {
    "rank": 2,
    "id": 18162663,
    "title": "Well-Architected Monoliths Are Okay",
    "url": "https://robertnorthard.com/devops-days-well-architected-monoliths-are-okay/",
    "score": 338,
    "by": "kiyanwang",
    "descendants": 190,
    "time": 1538947063
  },
  {
    "rank": 3,
    "id": 18164188,
    "title": "How to delete Facebook and not lose your friends and photos",
    "url": "https://ronaldlangeveld.com/deleting-facebook/",
    "score": 352,
    "by": "ronaldl93",
    "descendants": 174,
    "time": 1538973840
  },
  {
    "rank": 4,
    "id": 18164189,
    "title": "Ask HN: Cheap places to live with a good intellectual atmosphere?",
    "url": "https://news.ycombinator.com/item?id=18164189",
    "score": 911,
    "by": "throwawaygoaway",
    "descendants": 1088,
    "time": 1538973880
  },
  {
    "rank": 5,
    "id": 18165365,
    "title": "Tech Workers Now Want to Know: What Are We Building This For?",
    "url": "https://www.nytimes.com/2018/10/07/technology/tech-workers-ask-censorship-surveillance.html",
    "score": 418,
    "by": "siscia",
    "descendants": 339,
    "time": 1538987571
  },
  {
    "rank": 6,
    "id": 18166538,
    "title": "Show HN: Introducing the Alan low-code platform",
    "url": "https://alan-platform.com/pages/tuts/introducing.html",
    "score": 413,
    "by": "klageveen",
    "descendants": 173,
    "time": 1538999438
  },
  {
    "rank": 7,
    "id": 18168400,
    "title": "Calls between JavaScript and WebAssembly are finally fast",
    "url": "https://hacks.mozilla.org/2018/10/calls-between-javascript-and-webassembly-are-finally-fast-%f0%9f%8e%89/",
    "score": 907,
    "by": "lainon",
    "descendants": 143,
    "time": 1539013062
  },
  {
    "rank": 8,
    "id": 18168720,
    "title": "Today Is My Wife\u2019s First Birthday Since She Died",
    "url": "https://medium.com/@webwright/today-is-my-wifes-first-birthday-since-she-died-7369944c43ec",
    "score": 517,
    "by": "troydavis",
    "descendants": 86,
    "time": 1539015311
  },
  {
    "rank": 9,
    "id": 18169027,
    "title": "Google Exposed User Data, Feared Repercussions of Disclosing to Public",
    "url": "https://www.wsj.com/articles/google-exposed-user-data-feared-repercussions-of-disclosing-to-public-1539017194",
    "score": 953,
    "by": "tysone",
    "descendants": 258,
    "time": 1539017387
  },
  {
    "rank": 10,
    "id": 18169243,
    "title": "Shutting Down Google+ for Consumers",
    "url": "https://blog.google/technology/safety-security/project-strobe/",
    "score": 1613,
    "by": "Nemant",
    "descendants": 699,
    "time": 1539018879
  }
]
