[
  {
    "rank": 1,
    "id": 30128740,
    "title": "War Is a Racket (1933)",
    "url": "https://man.fas.org/smedley.htm",
    "score": 0,
    "by": "",
    "descendants": 0,
    "time": 0
  },
  {
    "rank": 2,
    "id": 30130251,
    "title": "Despite the hype, iPhone security no match for NSO spyware (2021)",
    "url": "https://www.washingtonpost.com/technology/2021/07/19/apple-iphone-nso/",
    "score": 0,
    "by": "",
    "descendants": 0,
    "time": 0
  },
  {
    "rank": 3,
    "id": 30130315,
    "title": "Black, the uncompromising Python code formatter, is stable",
    "url": "https://pypi.org/project/black/",
    "score": 0,
    "by": "",
    "descendants": 0,
    "time": 0
  },
  {
    "rank": 4,
    "id": 30131628,
    "title": "Phone is still the best way to order pizza",
    "url": "https://dan.bulwinkle.net/blog/phone-is-still-the-best-way-to-order-pizza/",
    "score": 0,
    "by": "",
    "descendants": 0,
    "time": 0
  },
  {
    "rank": 5,
    "id": 30132560,
    "title": "Ask HN: At a peak of my dev career, I hate my life",
    "url": "https://news.ycombinator.com/item?id=30132560",
    "score": 0,
    "by": "",
    "descendants": 0,
    "time": 0
  },
  {
    "rank": 6,
    "id": 30132612,
    "title": "John Locke\u2019s recipe for Pancakes (2021)",
    "url": "https://rarecooking.com/2021/12/14/john-lockes-recipe-for-pancakes/",
    "score": 0,
    "by": "",
    "descendants": 0,
    "time": 0
  },
  {
    "rank": 7,
    "id": 30134500,
    "title": "Did I just lose half a million dollars?",
    "url": "https://www.reddit.com/r/ethereum/comments/sfz4kw/did_i_just_lose_half_a_million_dollars_by_sending/",
    "score": 0,
    "by": "",
    "descendants": 0,
    "time": 0
  },
  {
    "rank": 8,
    "id": 30135264,
    "title": "GDPR penalty for passing on of IP address to Google by using Google Fonts",
    "url": "https://rewis.io/urteile/urteil/lhm-20-01-2022-3-o-1749320/",
    "score": 0,
    "by": "",
    "descendants": 0,
    "time": 0
  },
  {
    "rank": 9,
    "id": 30137984,
    "title": "Show HN: Web page that parses and explains the label on a bike tire",
    "url": "https://fahrrad-tools.de/tire.html",
    "score": 0,
    "by": "",
    "descendants": 0,
    "time": 0
  },
  {
    "rank": 10,
    "id": 30140984,
    "title": "A UX designer walks into a Tesla Bar",
    "url": "https://jenson.org/tesla/",
    "score": 0,
    "by": "",
    "descendants": 0,
    "time": 0
  }
]
