[
  {
    "rank": 1,
    "id": 12435583,
    "title": "How we unnecessarily burned 20k with Facebook Ads",
    "url": "https://www.stackfield.com/blog/how-we-unnecessarily-burned-20k-with-facebook-ads-43",
    "score": 280,
    "by": "rolfos",
    "descendants": 116,
    "time": 1473166525
  },
  {
    "rank": 2,
    "id": 12435976,
    "title": "Sri Lanka Is Declared Malaria Free by World Health Organization",
    "url": "http://blogs.wsj.com/indiarealtime/2016/09/06/sri-lanka-is-declared-malaria-free-by-world-health-organization/",
    "score": 323,
    "by": "known",
    "descendants": 33,
    "time": 1473170011
  },
  {
    "rank": 3,
    "id": 12437345,
    "title": "Announcing Quill 1.0",
    "url": "https://quilljs.com/blog/announcing-quill-1-0/",
    "score": 331,
    "by": "anurag",
    "descendants": 82,
    "time": 1473180561
  },
  {
    "rank": 4,
    "id": 12437572,
    "title": "How to get people who installed a leaked build to stop using that build?",
    "url": "https://blogs.msdn.microsoft.com/oldnewthing/20160906-00/?p=94255",
    "score": 354,
    "by": "runesoerensen",
    "descendants": 143,
    "time": 1473182308
  },
  {
    "rank": 5,
    "id": 12440612,
    "title": "Gordon Murray-designed \u2018OX\u2019 flat-pack truck",
    "url": "http://www.topgear.com/car-news/big-reads/can-flat-pack-truck-save-world",
    "score": 308,
    "by": "kaishiro",
    "descendants": 109,
    "time": 1473214801
  },
  {
    "rank": 6,
    "id": 12441703,
    "title": "PiBakery \u2013 a blocks based, easy to use setup tool for Raspberry Pi",
    "url": "http://www.pibakery.org/",
    "score": 291,
    "by": "trueduke",
    "descendants": 62,
    "time": 1473238006
  },
  {
    "rank": 7,
    "id": 12442048,
    "title": "How Google obliterated my 4 year old Chrome extension featuring 24k+ users",
    "url": "https://by.graffino.com/how-google-obliterated-my-24k-users-chrome-extension-eeb14c040a39#.13m3awp18",
    "score": 330,
    "by": "andygambles",
    "descendants": 244,
    "time": 1473243061
  },
  {
    "rank": 8,
    "id": 12443629,
    "title": "Lessons from a 45-year Study of Super-Smart Children",
    "url": "http://www.scientificamerican.com/article/how-to-raise-a-genius-lessons-from-a-45-year-study-of-super-smart-children/",
    "score": 490,
    "by": "kungfudoi",
    "descendants": 457,
    "time": 1473258352
  },
  {
    "rank": 9,
    "id": 12443994,
    "title": "\u2018Superbug\u2019 scourge spreads as U.S. fails to track rising human toll",
    "url": "http://www.reuters.com/investigates/special-report/usa-uncounted-surveillance/",
    "score": 300,
    "by": "danso",
    "descendants": 124,
    "time": 1473260819
  },
  {
    "rank": 10,
    "id": 12445994,
    "title": "iPhone 7",
    "url": "http://www.apple.com/iPhone7",
    "score": 756,
    "by": "benigeri",
    "descendants": 1733,
    "time": 1473274347
  }
]
