[
  {
    "rank": 1,
    "id": 28551205,
    "title": "WireGuard for Windows now uses high speed kernel implementation",
    "url": "https://twitter.com/EdgeSecurity/status/1437402720135270403",
    "score": 0,
    "by": "",
    "descendants": 0,
    "time": 0
  },
  {
    "rank": 2,
    "id": 28577951,
    "title": "AirGuard: Protect yourself from being tracked by AirTags and Find My accessories",
    "url": "https://github.com/seemoo-lab/AirGuard",
    "score": 0,
    "by": "",
    "descendants": 0,
    "time": 0
  },
  {
    "rank": 3,
    "id": 28578644,
    "title": "Excision's CRISPR HIV therapy is heading into human testing after FDA clearance",
    "url": "https://www.fiercebiotech.com/biotech/excision-hiv-crispr-gene-editing-therapy-cleared-for-human-studies-by-fda",
    "score": 0,
    "by": "",
    "descendants": 0,
    "time": 0
  },
  {
    "rank": 4,
    "id": 28579285,
    "title": "Can You See the Republic of Ireland from England?",
    "url": "https://www.anglezarke.net/can-you-see-the-republic-of-ireland-from-england/",
    "score": 0,
    "by": "",
    "descendants": 0,
    "time": 0
  },
  {
    "rank": 5,
    "id": 28579920,
    "title": "Amazon says it\u2019s permanently banned 600 Chinese brands for review fraud",
    "url": "https://www.theverge.com/2021/9/17/22680269/amazon-ban-chinese-brands-review-abuse-fraud-policy",
    "score": 0,
    "by": "",
    "descendants": 0,
    "time": 0
  },
  {
    "rank": 6,
    "id": 28582560,
    "title": "Russia restricts opposition election voting app",
    "url": "https://netblocks.org/reports/russia-restricts-opposition-election-voting-app-from-apple-app-store-and-google-play-store-JBZrPaB6",
    "score": 0,
    "by": "",
    "descendants": 0,
    "time": 0
  },
  {
    "rank": 7,
    "id": 28583680,
    "title": "University of Florida gets a 1% cut of Gatorade profits",
    "url": "https://thehustle.co/why-the-university-of-florida-gets-a-20m-cut-of-gatorade-profits-every-year/",
    "score": 0,
    "by": "",
    "descendants": 0,
    "time": 0
  },
  {
    "rank": 8,
    "id": 28584738,
    "title": "Serving Netflix Video at 400Gb/s on FreeBSD [pdf]",
    "url": "https://people.freebsd.org/~gallatin/talks/euro2021.pdf",
    "score": 0,
    "by": "",
    "descendants": 0,
    "time": 0
  },
  {
    "rank": 9,
    "id": 28585208,
    "title": "Show HN: Fully-searchable Library Genesis on IPFS",
    "url": "https://libgen.fun/dweb.html",
    "score": 0,
    "by": "",
    "descendants": 0,
    "time": 0
  },
  {
    "rank": 10,
    "id": 28585817,
    "title": "Bye YouTube, Hello PeerTube [video]",
    "url": "https://diode.zone/w/ooKHgZQnFkGjzbjZjRkZf7?autoplay=1&auto_play=true&start=4m19s",
    "score": 0,
    "by": "",
    "descendants": 0,
    "time": 0
  }
]
