[
  {
    "rank": 1,
    "id": 17470543,
    "title": "Is timeless UI design a thing?",
    "url": "https://www.imaginarycloud.com/blog/timeless-classic-ui-design/amp",
    "score": 0,
    "by": "",
    "descendants": 0,
    "time": 0
  },
  {
    "rank": 2,
    "id": 17482067,
    "title": "China Begins Production Of x86 Processors Based On AMD's IP",
    "url": "https://www.tomshardware.com/news/china-zen-x86-processor-dryhana,37417.html",
    "score": 0,
    "by": "",
    "descendants": 0,
    "time": 0
  },
  {
    "rank": 3,
    "id": 17485893,
    "title": "My favorite apps on F-Droid",
    "url": "http://quaap.com/D/use-fdroid",
    "score": 0,
    "by": "",
    "descendants": 0,
    "time": 0
  },
  {
    "rank": 4,
    "id": 17486040,
    "title": "Inside China\u2019s Dystopian Dreams: A.I., Shame and Lots of Cameras",
    "url": "https://www.nytimes.com/2018/07/08/business/china-surveillance-technology.html",
    "score": 0,
    "by": "",
    "descendants": 0,
    "time": 0
  },
  {
    "rank": 5,
    "id": 17487196,
    "title": "Apple\u2019s Shortcuts will flip the switch on Siri\u2019s potential",
    "url": "https://techcrunch.com/2018/07/08/shortcuts-will-flip-the-switch-for-apple-on-siris-potential-just-not-how-you-think/",
    "score": 0,
    "by": "",
    "descendants": 0,
    "time": 0
  },
  {
    "rank": 6,
    "id": 17487441,
    "title": "Choice of search engine on Android nuked by \u201cAnonymous Coward\u201d (2009)",
    "url": "https://android.googlesource.com/platform/packages/apps/GlobalSearch/+/592150ac00086400415afe936d96f04d3be3ba0c",
    "score": 0,
    "by": "",
    "descendants": 0,
    "time": 0
  },
  {
    "rank": 7,
    "id": 17488719,
    "title": "Illegal Production and Use of Banned CFC-11 in China's Foam Blowing Industry",
    "url": "https://eia-global.org/reports/20180709-blowing-it-illegal-production-and-use-of-banned-cfc-11-in-chinas-foam-blowing-industry",
    "score": 0,
    "by": "",
    "descendants": 0,
    "time": 0
  },
  {
    "rank": 8,
    "id": 17489934,
    "title": "Simple, correct, fast: in that order",
    "url": "https://drewdevault.com/2018/07/09/Simple-correct-fast.html",
    "score": 0,
    "by": "",
    "descendants": 0,
    "time": 0
  },
  {
    "rank": 9,
    "id": 17490319,
    "title": "Nissan Admits Internal Emissions-Test Data Was Falsified",
    "url": "https://www.wsj.com/articles/nissan-admits-emission-test-data-was-falsified-1531139749",
    "score": 0,
    "by": "",
    "descendants": 0,
    "time": 0
  },
  {
    "rank": 10,
    "id": 17492750,
    "title": "Half of ICOs Die Within Four Months After Token Sales Finalized",
    "url": "https://www.bloomberg.com/news/articles/2018-07-09/half-of-icos-die-within-four-months-after-token-sales-finalized",
    "score": 0,
    "by": "",
    "descendants": 0,
    "time": 0
  }
]
