[
  {
    "rank": 1,
    "id": 34665738,
    "title": "As a US Navy fighter pilot, I witnessed unidentified anomalous phenomena",
    "url": "https://thehill.com/opinion/national-security/3843075-as-a-us-navy-fighter-pilot-i-witnessed-unidentified-anomalous-phenomena-uap-congress-must-reveal-the-truth-to-the-american-people/",
    "score": 486,
    "by": "graderjs",
    "descendants": 939,
    "time": 1675611600
  },
  {
    "rank": 2,
    "id": 34666305,
    "title": "If you're happy with OpenBSD, probably any computer is good enough",
    "url": "http://muezza.ca/thoughts/openbsd_imac_g4/",
    "score": 417,
    "by": "BizarreByte",
    "descendants": 336,
    "time": 1675615331
  },
  {
    "rank": 3,
    "id": 34670136,
    "title": "Stable Attribution",
    "url": "https://www.stableattribution.com",
    "score": 747,
    "by": "mkeeter",
    "descendants": 349,
    "time": 1675635061
  },
  {
    "rank": 4,
    "id": 34673581,
    "title": "Path to a free, self-taught education in Computer Science",
    "url": "https://github.com/ossu/computer-science",
    "score": 691,
    "by": "netfortius",
    "descendants": 199,
    "time": 1675659950
  },
  {
    "rank": 5,
    "id": 34673949,
    "title": "Ask HN: Did anyone else lose their marbles?",
    "url": "https://news.ycombinator.com/item?id=34673949",
    "score": 568,
    "by": "throoowwawaayy",
    "descendants": 341,
    "time": 1675663601
  },
  {
    "rank": 6,
    "id": 34676186,
    "title": "How much can you get out of a $4 VPS?",
    "url": "https://alicegg.tech//2023/02/06/4dollar-vps.html",
    "score": 561,
    "by": "zer0tonin",
    "descendants": 484,
    "time": 1675684978
  },
  {
    "rank": 7,
    "id": 34677180,
    "title": "Tell HN: DEI initiatives undermine the self esteem of PoC within a company",
    "url": "https://news.ycombinator.com/item?id=34677180",
    "score": 1091,
    "by": "qzx_pierri",
    "descendants": 832,
    "time": 1675691138
  },
  {
    "rank": 8,
    "id": 34680903,
    "title": "The technology behind GitHub\u2019s new code search",
    "url": "https://github.blog/2023-02-06-the-technology-behind-githubs-new-code-search/",
    "score": 750,
    "by": "joshbetz",
    "descendants": 181,
    "time": 1675704764
  },
  {
    "rank": 9,
    "id": 34681636,
    "title": "Voice.ai: GPL Violations with a Side of DRM",
    "url": "https://undeleted.ronsor.com/voice.ai-gpl-violations-with-a-side-of-drm/",
    "score": 598,
    "by": "ronsor",
    "descendants": 209,
    "time": 1675707358
  },
  {
    "rank": 10,
    "id": 34682340,
    "title": "Bard and new AI features in Search",
    "url": "https://blog.google/technology/ai/bard-google-ai-search-updates/",
    "score": 988,
    "by": "jmsflknr",
    "descendants": 954,
    "time": 1675710105
  }
]
