[
  {
    "rank": 1,
    "id": 1655937,
    "title": "Rate my iPhone app: cooking recipes as Gantt charts. Tell me what you think.",
    "url": "http://kangasbros.fi/visual-cookbook/",
    "score": 144,
    "by": "jerguismi",
    "descendants": 67,
    "time": 1283430157
  },
  {
    "rank": 2,
    "id": 1656057,
    "title": "Building a Scrabble MMO in 48 hours",
    "url": "http://www.startupmonkeys.com/2010/09/building-a-scrabble-mmo-in-48-hours/",
    "score": 137,
    "by": "railsjedi",
    "descendants": 30,
    "time": 1283433925
  },
  {
    "rank": 3,
    "id": 1657120,
    "title": "CSS3 Buttons",
    "url": "http://lab.simurai.com/css/buttons/",
    "score": 168,
    "by": "alexkiwi",
    "descendants": 41,
    "time": 1283452006
  },
  {
    "rank": 4,
    "id": 1657281,
    "title": "Craig Newmark: How Being a Geek Made it Hard to Respond to CNN's Ambush",
    "url": "http://thefastertimes.com/techlife/2010/09/02/craig-newmark-what-i-should-have-said-to-cnns-amber-lyon-when-she-ambushed-me/",
    "score": 187,
    "by": "dreambird",
    "descendants": 72,
    "time": 1283454992
  },
  {
    "rank": 5,
    "id": 1658022,
    "title": "India's red rain may contain life not seen on Earth",
    "url": "http://www.news.com.au/technology/panspermia-theorists-say-indias-red-rain-contains-life-not-seen-on-earth/story-e6frfro0-1225913620448",
    "score": 137,
    "by": "keyle",
    "descendants": 67,
    "time": 1283468100
  },
  {
    "rank": 6,
    "id": 1658280,
    "title": "Google Wave open source next steps: \"Wave in a Box\"",
    "url": "http://googlewavedev.blogspot.com/2010/09/wave-open-source-next-steps-wave-in-box.html?utm_source=feedburner&utm_medium=feed&utm_campaign=Feed%3A+GoogleWaveDeveloperBlog+%28Google+Wave+Developer+Blog%29",
    "score": 153,
    "by": "jolie",
    "descendants": 26,
    "time": 1283476603
  },
  {
    "rank": 7,
    "id": 1659306,
    "title": "Apple's ping is a big pile of steaming dung",
    "url": "http://swizec.com/blog/apples-ping-is-a-big-pile-of-steaming-dung/swizec/1444",
    "score": 158,
    "by": "Swizec",
    "descendants": 105,
    "time": 1283516494
  },
  {
    "rank": 8,
    "id": 1659409,
    "title": "Ask HN: Who's hiring? (September 2010)",
    "url": "http://news.ycombinator.com/item?id=1659409",
    "score": 176,
    "by": "buro9",
    "descendants": 236,
    "time": 1283519353
  },
  {
    "rank": 9,
    "id": 1659897,
    "title": "Timing Lessons",
    "url": "http://www.bizstone.com/2010/09/timing-lessons.html",
    "score": 165,
    "by": "dabent",
    "descendants": 37,
    "time": 1283528057
  },
  {
    "rank": 10,
    "id": 1660096,
    "title": "Bill Gates: \"Someone decided to trash the one part of Windows that was usable?\"",
    "url": "http://blog.seattlepi.com/microsoft/archives/141821.asp",
    "score": 375,
    "by": "paolomaffei",
    "descendants": 212,
    "time": 1283531093
  }
]
