[
  {
    "rank": 1,
    "id": 32938305,
    "title": "Censorship by big tech at the behest of the U.S. government?",
    "url": "https://www.tabletmag.com/sections/arts-letters/articles/government-privatized-censorship-regime",
    "score": 422,
    "by": "dilap",
    "descendants": 758,
    "time": 1663852183
  },
  {
    "rank": 2,
    "id": 32945906,
    "title": "Avoiding homework with code and getting caught",
    "url": "https://alistair.blog/mochip",
    "score": 766,
    "by": "aabbccsmith",
    "descendants": 160,
    "time": 1663888800
  },
  {
    "rank": 3,
    "id": 32946012,
    "title": "We Need New Motherboards Before GPUs Collapse Under Their Own Gravity",
    "url": "https://erikmcclure.com/blog/we-need-new-motherboards/",
    "score": 312,
    "by": "blackhole",
    "descendants": 348,
    "time": 1663889569
  },
  {
    "rank": 4,
    "id": 32947303,
    "title": "Nightdrive",
    "url": "https://incoherency.co.uk/blog/stories/nightdrive.html",
    "score": 1440,
    "by": "GeorgeHahn",
    "descendants": 240,
    "time": 1663900180
  },
  {
    "rank": 5,
    "id": 32950204,
    "title": "Ask HN: Ads triggered by WhatsApp \u201cend to end encrypted\u201d messages?",
    "url": "https://news.ycombinator.com/item?id=32950204",
    "score": 398,
    "by": "rreyes1979",
    "descendants": 452,
    "time": 1663930549
  },
  {
    "rank": 6,
    "id": 32950408,
    "title": "Matrix web-based green code rain, made with love",
    "url": "https://github.com/Rezmason/matrix",
    "score": 389,
    "by": "DerWOK",
    "descendants": 67,
    "time": 1663932442
  },
  {
    "rank": 7,
    "id": 32950442,
    "title": "The journey to Nintendo Switch",
    "url": "https://factorio.com/blog/post/fff-370",
    "score": 375,
    "by": "snthueoa",
    "descendants": 165,
    "time": 1663932676
  },
  {
    "rank": 8,
    "id": 32950988,
    "title": "The road to Zettalinux",
    "url": "https://lwn.net/SubscriberLink/908026/6284e31d9060a6ec/",
    "score": 301,
    "by": "rwmj",
    "descendants": 194,
    "time": 1663936128
  },
  {
    "rank": 9,
    "id": 32953732,
    "title": "Software I\u2019m thankful for (2021)",
    "url": "https://crawshaw.io/blog/thankful-for-technology",
    "score": 813,
    "by": "yarapavan",
    "descendants": 509,
    "time": 1663948967
  },
  {
    "rank": 10,
    "id": 32956964,
    "title": "The image in this post displays its own MD5 hash",
    "url": "https://retr0.id/notice/ANqlvFZD1eIqjmRiFc",
    "score": 766,
    "by": "kstrauser",
    "descendants": 130,
    "time": 1663966680
  }
]
