[
  {
    "rank": 1,
    "id": 9634611,
    "title": "FBI doesnt want you to know it uses NSLs to correlate identities you use online",
    "url": "https://www.emptywheel.net/2015/05/31/fbi-doesnt-want-you-to-know-it-uses-nsls-to-correlate-all-the-identities-you-use-online/",
    "score": 197,
    "by": "cinquemb",
    "descendants": 24,
    "time": 1433089639
  },
  {
    "rank": 2,
    "id": 9635076,
    "title": "Apple I discarded as junk sells for $200k; mystery woman stands to get half",
    "url": "http://www.mercurynews.com/business/ci_28221648/100-000-check-awaits-mystery-apple-i-donor",
    "score": 208,
    "by": "mmastrac",
    "descendants": 69,
    "time": 1433097839
  },
  {
    "rank": 3,
    "id": 9636450,
    "title": "Section 215 Expires For Now",
    "url": "https://www.eff.org/deeplinks/2015/05/section-215-expires-now",
    "score": 471,
    "by": "DiabloD3",
    "descendants": 158,
    "time": 1433124435
  },
  {
    "rank": 4,
    "id": 9637061,
    "title": "Dear Paul",
    "url": "http://zedshaw.com/2015/06/01/dear-paul/",
    "score": 469,
    "by": "barbs",
    "descendants": 168,
    "time": 1433141214
  },
  {
    "rank": 5,
    "id": 9637292,
    "title": "Hello World: Windows 10 Available on July 29",
    "url": "http://blogs.windows.com/bloggingwindows/2015/06/01/hello-world-windows-10-available-on-july-29/",
    "score": 229,
    "by": "tolt",
    "descendants": 234,
    "time": 1433146460
  },
  {
    "rank": 6,
    "id": 9637649,
    "title": "Securing Email Communications from Facebook",
    "url": "https://www.facebook.com/notes/protecting-the-graph/securing-email-communications-from-facebook/1611941762379302",
    "score": 399,
    "by": "wrboyce",
    "descendants": 164,
    "time": 1433154757
  },
  {
    "rank": 7,
    "id": 9638070,
    "title": "Intel Buys Altera for $16.7B",
    "url": "http://www.bloomberg.com/news/articles/2015-06-01/intel-buys-altera-for-16-7-billion-as-chip-deals-accelerate",
    "score": 339,
    "by": "rbanffy",
    "descendants": 140,
    "time": 1433162417
  },
  {
    "rank": 8,
    "id": 9638305,
    "title": "Is ReactJS really fast?",
    "url": "http://blog.500tech.com/is-reactjs-fast/",
    "score": 409,
    "by": "Murkin",
    "descendants": 186,
    "time": 1433164974
  },
  {
    "rank": 9,
    "id": 9639001,
    "title": "Ask HN: Who is hiring? (June 2015)",
    "url": "https://news.ycombinator.com/item?id=9639001",
    "score": 429,
    "by": "whoishiring",
    "descendants": 777,
    "time": 1433170502
  },
  {
    "rank": 10,
    "id": 9640404,
    "title": "Microsoft Buys German To-Do List Startup 6Wunderkinder",
    "url": "http://www.wsj.com/articles/microsoft-buys-german-to-do-list-startup-6wunderkinder-1433177558?mod=yahoo_hs&ref=yfp",
    "score": 293,
    "by": "abetaha",
    "descendants": 132,
    "time": 1433179229
  }
]
