[
  {
    "rank": 1,
    "id": 33033017,
    "title": "Get things done with Emacs",
    "url": "https://www.labri.fr/perso/nrougier/GTD/index.html",
    "score": 292,
    "by": "ducktective",
    "descendants": 80,
    "time": 1664532773
  },
  {
    "rank": 2,
    "id": 33035580,
    "title": "Show HN: uFuzzy.js \u2013 A tiny, efficient fuzzy search that doesn't suck",
    "url": "https://github.com/leeoniya/uFuzzy",
    "score": 251,
    "by": "leeoniya",
    "descendants": 82,
    "time": 1664549089
  },
  {
    "rank": 3,
    "id": 33037319,
    "title": "House Democrats debut new bill to limit US police use of facial recognition",
    "url": "https://techcrunch.com/2022/09/29/house-democrats-facial-recognition-act/",
    "score": 322,
    "by": "arkadiyt",
    "descendants": 151,
    "time": 1664556898
  },
  {
    "rank": 4,
    "id": 33040873,
    "title": "Citrix acquired and merged with Tibco for $16.5B",
    "url": "https://www.cloud.com/news/press-release.html",
    "score": 269,
    "by": "avrionov",
    "descendants": 174,
    "time": 1664572351
  },
  {
    "rank": 5,
    "id": 33041733,
    "title": "Hacking Google",
    "url": "https://h4ck1ng.google",
    "score": 351,
    "by": "foxTN",
    "descendants": 157,
    "time": 1664578170
  },
  {
    "rank": 6,
    "id": 33045219,
    "title": "The 'Egg' Laptop",
    "url": "https://www.ikejima.org/projects/2022091-egg-laptop.html",
    "score": 419,
    "by": "rcarmo",
    "descendants": 71,
    "time": 1664616111
  },
  {
    "rank": 7,
    "id": 33045546,
    "title": "Paris Will Become \u2018100% Cyclable\u2019",
    "url": "https://www.bloomberg.com/news/articles/2021-10-22/how-paris-will-become-100-cyclable",
    "score": 287,
    "by": "tosh",
    "descendants": 194,
    "time": 1664620765
  },
  {
    "rank": 8,
    "id": 33045763,
    "title": "Enhanced noise suppression in Jitsi Meet",
    "url": "https://jitsi.org/blog/enhanced-noise-suppression-in-jitsi-meet/",
    "score": 322,
    "by": "jlpcsl",
    "descendants": 85,
    "time": 1664623680
  },
  {
    "rank": 9,
    "id": 33047150,
    "title": "A surprising way to lose your files on Windows",
    "url": "https://news.ycombinator.com/item?id=33047150",
    "score": 366,
    "by": "raffraffraff",
    "descendants": 244,
    "time": 1664636935
  },
  {
    "rank": 10,
    "id": 33047199,
    "title": "The self-taught UI/UX designer roadmap (2021)",
    "url": "https://bootcamp.uxdesign.cc/the-self-taught-ui-ux-designer-roadmap-in-2021-aa0f5b62cecb",
    "score": 371,
    "by": "homarp",
    "descendants": 102,
    "time": 1664637362
  }
]
