[
  {
    "rank": 1,
    "id": 23701394,
    "title": "Not a Wheelchair [video]",
    "url": "https://www.youtube.com/watch?v=vuMg0QwKAGI",
    "score": 354,
    "by": "priyanmuthu",
    "descendants": 144,
    "time": 1593612104
  },
  {
    "rank": 2,
    "id": 23702552,
    "title": "Lights and Shadows",
    "url": "https://ciechanow.ski/lights-and-shadows/",
    "score": 386,
    "by": "robert-boehnke",
    "descendants": 28,
    "time": 1593617413
  },
  {
    "rank": 3,
    "id": 23704123,
    "title": "A Google bot scrapes pricing info by adding items to carts",
    "url": "https://www.wsj.com/articles/who-is-the-mystery-shopper-leaving-behind-all-those-online-shopping-carts-11593617464",
    "score": 362,
    "by": "psim1",
    "descendants": 277,
    "time": 1593624749
  },
  {
    "rank": 4,
    "id": 23704497,
    "title": "How the 2021 Ford F-150's onboard generator works",
    "url": "https://www.roadandtrack.com/new-cars/car-technology/a32970167/f-150-generator-pro-power-onboard/",
    "score": 349,
    "by": "hirundo",
    "descendants": 508,
    "time": 1593626669
  },
  {
    "rank": 5,
    "id": 23705546,
    "title": "Apple Lightning",
    "url": "https://nyansatan.github.io/lightning/",
    "score": 597,
    "by": "captn3m0",
    "descendants": 229,
    "time": 1593632238
  },
  {
    "rank": 6,
    "id": 23708166,
    "title": "DuckDuckGo browser seemingly sends domains a user visits to DDG servers",
    "url": "https://github.com/duckduckgo/Android/issues/527",
    "score": 824,
    "by": "commotionfever",
    "descendants": 488,
    "time": 1593646742
  },
  {
    "rank": 7,
    "id": 23709016,
    "title": "Space Jam's 1996 website is still alive",
    "url": "https://www.spacejam.com/",
    "score": 707,
    "by": "olingern",
    "descendants": 266,
    "time": 1593653546
  },
  {
    "rank": 8,
    "id": 23710551,
    "title": "The Sci-Hub Effect: Sci-Hub downloads lead to more article citations",
    "url": "https://arxiv.org/abs/2006.14979",
    "score": 754,
    "by": "lnyan",
    "descendants": 92,
    "time": 1593671141
  },
  {
    "rank": 9,
    "id": 23714875,
    "title": "Abstract Wikipedia",
    "url": "https://meta.wikimedia.org/wiki/Abstract_Wikipedia/June_2020_announcement",
    "score": 798,
    "by": "infodocket",
    "descendants": 227,
    "time": 1593706666
  },
  {
    "rank": 10,
    "id": 23716451,
    "title": "LinkedIn is copying the contents of my clipboard on every keystroke",
    "url": "https://twitter.com/doncubed/status/1278757106468806656",
    "score": 928,
    "by": "dondonleroy",
    "descendants": 360,
    "time": 1593714828
  }
]
